nplus1loader/__init__.py
nplus1loader/bulk_load.py
nplus1loader/exc.py
nplus1loader/loadopt.py
nplus1loader/strategies.py
nplus1loader-1.0.1.dist-info/LICENSE
nplus1loader-1.0.1.dist-info/METADATA
nplus1loader-1.0.1.dist-info/WHEEL
nplus1loader-1.0.1.dist-info/top_level.txt
nplus1loader-1.0.1.dist-info/RECORD
