Metadata-Version: 2.1
Name: nplus1loader
Version: 1.0.1
Summary: SqlAlchemy N+1 Loader: a solution to the N+1 problem 
Home-page: https://github.com/kolypto/py-nplus1loader
Author: Mark Vartanyan
Author-email: kolypto@gmail.com
License: BSD
Keywords: sqlalchemy,nplus1
Platform: any
Classifier: Programming Language :: Python :: 3
Classifier: Development Status :: 5 - Production/Stable
Classifier: Intended Audience :: Developers
Classifier: Operating System :: OS Independent
Requires-Python: >= 3.6
Requires-Dist: sqlalchemy (>=1.3.0)
Requires-Dist: funcy
